MANIFEST.in
README.md
pip-requirements.txt
setup.py
pid_controller/__init__.py
pid_controller/pid.py
pid_controller/tests.py
pid_controller.egg-info/PKG-INFO
pid_controller.egg-info/SOURCES.txt
pid_controller.egg-info/dependency_links.txt
pid_controller.egg-info/not-zip-safe
pid_controller.egg-info/requires.txt
pid_controller.egg-info/top_level.txt