Metadata-Version: 1.0
Name: pid-controller
Version: 0.2.0
Summary: Simple PID controller implementation
Home-page: http://github.com/chrisspen/pid_controller
Author: Chris Spencer
Author-email: chrisspen@gmail.com
License: BSD
Platform: UNKNOWN
